andreo/__init__.py
andreo/__par__.py
andreo/__return__.py
andreo1-0.0.1.dist-info/LICENSE.txt
andreo1-0.0.1.dist-info/METADATA
andreo1-0.0.1.dist-info/WHEEL
andreo1-0.0.1.dist-info/top_level.txt
andreo1-0.0.1.dist-info/RECORD
