Metadata-Version: 2.1
Name: andreo1
Version: 0.0.1
Summary: Read text or text in images inside a pdf and turn it into string
Author: Andreo Naymayer
Author-email: andreocelular@gmail.com
License: UNKNOWN
Keywords: EN: convert pdf to text with option to cut images. BR: converte pdf para texto podendo cortar as imagens
Platform: UNKNOWN
Classifier: Programming Language :: Python :: 3
Classifier: License :: Other/Proprietary License
Classifier: Operating System :: OS Independent
Classifier: Natural Language :: Portuguese (Brazilian)
License-File: LICENSE.txt
Requires-Dist: numpy
Requires-Dist: pytesseract
Requires-Dist: opencv-python
